{
    "rocket":{
        "file":"images/rocket.gif",
        "rotation":0,
        "resize":true
    },
    "dance":{
        "file":"images/dance.gif",
        "rotation":0,
        "resize":true
    },
    "fire":{
        "file":"images/fire.gif",
        "rotation":0,
        "resize":true
    },
    "smoke":{
        "file":"images/smoke.gif",
        "rotation":0,
        "resize":true
    },
    "sleep":{
        "file":"images/sleep.gif",
        "rotation":0,
        "resize":true
    },
    "leds":{
        "file":"images/leds.gif",
        "rotation":0,
        "resize":true
    },
    "glasses":{
        "file":"images/turtle_glasses.png",
        "rotation":0,
        "resize":true
    },
    "glasses_large":{
        "file":"images/turtle_glasses_large.png",
        "rotation":0,
        "resize":true
    },
    "happy":{
        "file":"images/turtle_happy.png",
        "rotation":0,
        "resize":true
    },
    "rocket_turtle":{
        "file":"images/turtle_rocket.png",
        "rotation":0,
        "resize":true
    },
    "walking":{
        "file":"images/turtle_walking.png",
        "rotation":0,
        "resize":true
    }
}